llm/__init__.py
llm/cli.py
llm/commands.py
llm/config.py
llm/file_expander.py
llm/hf_auth.py
llm/history.py
llm/server.py
llm/setup.py
llm/update.py
pip_boy_llm-1.0.9.dist-info/METADATA
pip_boy_llm-1.0.9.dist-info/WHEEL
pip_boy_llm-1.0.9.dist-info/entry_points.txt
pip_boy_llm-1.0.9.dist-info/top_level.txt
pip_boy_llm-1.0.9.dist-info/RECORD
