Metadata-Version: 2.4
Name: pip-boy-llm
Version: 1.0.9
Summary: PIP-BOY LLM - Vault-Tec Local AI Terminal
License: MIT
Keywords: llm,ai,chatbot,mistral,llama,local
Requires-Python: >=3.9
Requires-Dist: flask>=2.0
Requires-Dist: flask-cors>=3.0
Requires-Dist: requests>=2.25
Requires-Dist: torch>=2.0
Requires-Dist: transformers>=4.35
Requires-Dist: accelerate>=0.20
Requires-Dist: huggingface_hub>=0.19
Requires-Dist: pyyaml>=6.0
Requires-Dist: packaging>=21.0
Provides-Extra: quantization
Requires-Dist: bitsandbytes>=0.41; extra == "quantization"
Provides-Extra: pdf
Requires-Dist: PyPDF2>=3.0; extra == "pdf"
Provides-Extra: readline
Requires-Dist: pyreadline3>=3.4; sys_platform == "win32" and extra == "readline"
Provides-Extra: all
Requires-Dist: pip-boy-llm[pdf,quantization,readline]; extra == "all"
